BJSCP/CP.py
BJSCP/__init__.py
BJSCP/build/lib/CP.py
BJSCP-0.0.3.dist-info/LICENSE
BJSCP-0.0.3.dist-info/METADATA
BJSCP-0.0.3.dist-info/WHEEL
BJSCP-0.0.3.dist-info/top_level.txt
BJSCP-0.0.3.dist-info/RECORD
